Metadata-Version: 1.0
Name: b3notify
Version: 0.1.1
Summary: Build status notifier for bitbucket server
Home-page: UNKNOWN
Author: Dinesh Weerapurage
Author-email: dinesh.weerapurage@pearson.com
License: UNKNOWN
Platform: UNKNOWN
